odoo/addons/stock_picking_consolidation_priority/README.rst
odoo/addons/stock_picking_consolidation_priority/__init__.py
odoo/addons/stock_picking_consolidation_priority/__manifest__.py
odoo/addons/stock_picking_consolidation_priority/i18n/es_AR.po
odoo/addons/stock_picking_consolidation_priority/i18n/it.po
odoo/addons/stock_picking_consolidation_priority/i18n/stock_picking_consolidation_priority.pot
odoo/addons/stock_picking_consolidation_priority/models/__init__.py
odoo/addons/stock_picking_consolidation_priority/models/stock_move.py
odoo/addons/stock_picking_consolidation_priority/models/stock_picking_type.py
odoo/addons/stock_picking_consolidation_priority/readme/CONFIGURATION.rst
odoo/addons/stock_picking_consolidation_priority/readme/CONTRIBUTORS.md
odoo/addons/stock_picking_consolidation_priority/readme/DESCRIPTION.md
odoo/addons/stock_picking_consolidation_priority/readme/ROADMAP.md
odoo/addons/stock_picking_consolidation_priority/static/description/icon.png
odoo/addons/stock_picking_consolidation_priority/static/description/index.html
odoo/addons/stock_picking_consolidation_priority/tests/__init__.py
odoo/addons/stock_picking_consolidation_priority/tests/test_consolidation_priority.py
odoo/addons/stock_picking_consolidation_priority/views/stock_picking_type.xml
odoo_addon_stock_picking_consolidation_priority-18.0.1.0.0.2.dist-info/METADATA
odoo_addon_stock_picking_consolidation_priority-18.0.1.0.0.2.dist-info/WHEEL
odoo_addon_stock_picking_consolidation_priority-18.0.1.0.0.2.dist-info/top_level.txt
odoo_addon_stock_picking_consolidation_priority-18.0.1.0.0.2.dist-info/RECORD
